autohash/__init__.py
autohash-0.0.1.dist-info/LICENSE
autohash-0.0.1.dist-info/METADATA
autohash-0.0.1.dist-info/WHEEL
autohash-0.0.1.dist-info/top_level.txt
autohash-0.0.1.dist-info/RECORD
