Metadata-Version: 2.1
Name: autohash
Version: 0.0.1
Summary: Hashes nonhashable / mutable objects
Home-page: https://github.com/bra-fsn/autohash
Author: NAGY, Attila
Author-email: nagy.attila@gmail.com
License: UNKNOWN
Platform: UNKNOWN
Classifier: Programming Language :: Python
Classifier: License :: OSI Approved :: MIT License
Classifier: Operating System :: OS Independent
